multimetricprog/__init__.py
multimetricprog/__main__.py
multimetricprog/calculator.py
multimetricprog/fp.py
multimetricprog/cls/__init__.py
multimetricprog/cls/base.py
multimetricprog/cls/base_calc.py
multimetricprog/cls/base_stats.py
multimetricprog/cls/modules.py
multimetricprog/cls/calc/__init__.py
multimetricprog/cls/calc/halstead.py
multimetricprog/cls/calc/maintenance.py
multimetricprog/cls/calc/pylint.py
multimetricprog/cls/calc/tiobe.py
multimetricprog/cls/importer/__init__.py
multimetricprog/cls/importer/base.py
multimetricprog/cls/importer/filtered.py
multimetricprog/cls/importer/pick.py
multimetricprog/cls/importer/mods/__init__.py
multimetricprog/cls/importer/mods/csv.py
multimetricprog/cls/importer/mods/json.py
multimetricprog/cls/metric/__init__.py
multimetricprog/cls/metric/comments.py
multimetricprog/cls/metric/cyclomatic.py
multimetricprog/cls/metric/fanout.py
multimetricprog/cls/metric/loc.py
multimetricprog/cls/metric/operands.py
multimetricprog/cls/metric/operators.py
multimetricprog/cls/stats/__init__.py
multimetricprog/cls/stats/stats.py
multimetricprog-0.0.3.dist-info/LICENSE
multimetricprog-0.0.3.dist-info/METADATA
multimetricprog-0.0.3.dist-info/WHEEL
multimetricprog-0.0.3.dist-info/top_level.txt
multimetricprog-0.0.3.dist-info/RECORD
