Metadata-Version: 2.1
Name: multimetricprog
Version: 0.0.3
Summary: Calculate code metrics in various languages
Home-page: https://github.com/VadokDev/multimetric-programmatically
Author: Konrad Weihmann
Author-email: Gonzalo Fernández <gonzalo.fdez06@gmail.com>, Konrad Weihmann <kweihmann@outlook.com>
Project-URL: Homepage, https://github.com/VadokDev/multimetric-programmatically
Project-URL: Bug Tracker, https://github.com/VadokDev/multimetric-programmatically/issues
Classifier: Programming Language :: Python :: 3
Classifier: License :: OSI Approved :: MIT License
Classifier: Operating System :: OS Independent
Requires-Python: >=3.7
License-File: LICENSE
Requires-Dist: chardet (==5.1.0)
Requires-Dist: pygments (==2.15.1)
